teneva_jax/__init__.py
teneva_jax/act_one.py
teneva_jax/act_two.py
teneva_jax/als.py
teneva_jax/cross.py
teneva_jax/data.py
teneva_jax/maxvol.py
teneva_jax/sample.py
teneva_jax/svd.py
teneva_jax/tensors.py
teneva_jax/transformation.py
teneva_jax/vis.py
teneva_jax-0.1.1.dist-info/LICENSE.txt
teneva_jax-0.1.1.dist-info/METADATA
teneva_jax-0.1.1.dist-info/WHEEL
teneva_jax-0.1.1.dist-info/top_level.txt
teneva_jax-0.1.1.dist-info/RECORD
